yelp_fetcher/__init__.py
yelp_fetcher/_util.py
yelp_fetcher/exceptions.py
yelp_fetcher/metadata.py
yelp_fetcher/reviews.py
yelp_fetcher/statuses.py
yelp_fetcher/scraper/__init__.py
yelp_fetcher/scraper/biz.py
yelp_fetcher/scraper/bs4_util.py
yelp_fetcher/scraper/common.py
yelp_fetcher/scraper/user_details.py
yelp_fetcher/scraper/user_details_reviews_self.py
yelp_lambda/__init__.py
yelp_lambda/common_types.py
yelp_lambda/dispatcher_types.py
yelp_lambda/worker_types.py
yelp_common-2.0.2.dist-info/METADATA
yelp_common-2.0.2.dist-info/WHEEL
yelp_common-2.0.2.dist-info/top_level.txt
yelp_common-2.0.2.dist-info/RECORD
