Metadata-Version: 2.1
Name: yelp-common
Version: 2.0.2
Summary: UNKNOWN
Home-page: https://github.com/sampromises/yelp-common
Author: Sam Kim
Author-email: samkim90274@gmail.com
License: UNKNOWN
Platform: UNKNOWN
Requires-Python: >=3.8
Requires-Dist: bs4
Requires-Dist: requests
Requires-Dist: dateparser
